m3py/__init__.py
m3py/m3py.py
m3py-0.0.1.dist-info/METADATA
m3py-0.0.1.dist-info/WHEEL
m3py-0.0.1.dist-info/top_level.txt
m3py-0.0.1.dist-info/RECORD
