Metadata-Version: 2.1
Name: m3py
Version: 0.0.1
Summary: "Pseudo" (min) Processing API module, based on tkinter, for Python.
Home-page: https://github.com/KouichiMatsuda/m3py
Author: MATSUDA, Kouichi
Author-email: kouichi.matsuda@gmail.com
License: MIT
Keywords: Processing graphics library
Platform: UNKNOWN
Classifier: License :: OSI Approved :: MIT License
Classifier: Programming Language :: Python :: 3.6
